{
   "alias_info" : {},
   "app_key" : "application.generated.unity.conductvr.exe",
   "bindings" : {
      "/actions/buggy" : {
         "chords" : [],
         "haptics" : [],
         "poses" : [],
         "skeleton" : [],
         "sources" : []
      },
      "/actions/conductor" : {
         "chords" : [],
         "haptics" : [],
         "poses" : [
            {
               "output" : "/actions/conductor/in/poseleft",
               "path" : "/user/hand/left/pose/raw"
            },
            {
               "output" : "/actions/conductor/in/poseright",
               "path" : "/user/hand/right/pose/raw"
            }
         ],
         "skeleton" : [],
         "sources" : [
            {
               "inputs" : {
                  "click" : {
                     "output" : "/actions/conductor/in/conduct"
                  }
               },
               "mode" : "trigger",
               "path" : "/user/hand/right/input/trigger"
            }
         ]
      },
      "/actions/default" : {
         "chords" : [],
         "haptics" : [],
         "poses" : [],
         "skeleton" : [],
         "sources" : []
      },
      "/actions/platformer" : {
         "chords" : [],
         "haptics" : [],
         "poses" : [],
         "skeleton" : [],
         "sources" : []
      }
   },
   "controller_type" : "vive_controller",
   "description" : "",
   "name" : "vive_controller",
   "options" : {},
   "simulated_actions" : []
}
